rtm_fast/__init__.py
rtm_fast/ds/__init__.py
rtm_fast/ds/common_function.py
rtm_fast/ds/common_utilities_registry.py
rtm_fast/ds/config_data_registry.py
rtm_fast/ds/ds_code_registry.py
rtm_fast/ds/requirements.txt
rtm_fast/ds/library/__init__.py
rtm_fast/ds/library/ds_code_test_measurement.py
rtm_fast/ds/library/ds_code_test_plan.py
rtm_fast/ds/library/ds_common_functions.py
rtm_fast/ds/library/ds/__init__.py
rtm_fast/ds/library/ds/feature/cntrl_store_gen/cntrl_stores_master.py
rtm_fast/ds/library/ds/feature/rsv_estimation/rsv_estimate_master.py
rtm_fast/ds/library/ds/feature/target_estimation/target_estimate_master.py
rtm_fast/ds/library/ds/feature/test_measurement_cal/test_measurement_master.py
rtm_fast/ds/library/ds/feature/test_store_gen/test_stores_master.py
rtm_fast/ds/library/object_creation/__init__.py
rtm_fast/ds/library/object_creation/create_object.py
rtm_fast/ds/library/sql/__init__.py
rtm_fast/ds/library/sql/sales_master.py
rtm_fast/ds/library/sql/stores_master.py
rtm_fast/ds/library/sql/utility/__init__.py
rtm_fast/ds/library/sql/utility/sql_utility.py
rtm_fast/ds/regions/__init__.py
rtm_fast/ds/regions/UK/__init__.py
rtm_fast/ds/regions/UK/common_utility.py
rtm_fast/ds/regions/UK/config_data.py
rtm_fast/ds/regions/UK/ds_code.py
rtm_fast/ds/regions/UK/upload_templates/Control_Pairs_Pool_Upload_Template_UK.xlsx
rtm_fast/ds/regions/UK/upload_templates/Test_Control_Pairs_Upload_Template_UK.xlsx
rtm_fast/ds/regions/UK/upload_templates/Upload_Population_Template_UK.xlsx
rtm_fast/ds/regions/UK/upload_templates/Upload_Teststores_Template_UK.xlsx
rtm_fast/ds/regions/US/__init__.py
rtm_fast/ds/regions/US/common_utility.py
rtm_fast/ds/regions/US/config_data.py
rtm_fast/ds/regions/US/ds_code.py
rtm_fast/ds/regions/US/upload_templates/Control_Pairs_Pool_Upload_Template_US.xlsx
rtm_fast/ds/regions/US/upload_templates/Test_Control_Pairs_Upload_Template_US.xlsx
rtm_fast/ds/regions/US/upload_templates/Upload_Population_Template_US.xlsx
rtm_fast-0.0.2.dist-info/METADATA
rtm_fast-0.0.2.dist-info/WHEEL
rtm_fast-0.0.2.dist-info/licenses/LICENSE
rtm_fast-0.0.2.dist-info/RECORD
